{
  "hash": "67a1bb66378007aa0ff010984bddbc3e",
  "result": {
    "engine": "knitr",
    "markdown": "---\ntitle: \"Triplets of graph\"\nexecute:\n  freeze: true\n---\n\n\n\n*R/gf_interface.R*\n\n## gf_triplets\n\n## Description\n Triplets of graph \n\n\n## Usage\n```r\n \ngf_triplets(x) \n```\n\n## Arguments\n|Arguments|Description|\n|---|---|\n| x | An object coercable to a GraphFrame (typically, a `gf_graphframe`). |\n\n\n\n\n\n\n\n\n\n",
    "supporting": [],
    "filters": [
      "rmarkdown/pagebreak.lua"
    ],
    "includes": {},
    "engineDependencies": {},
    "preserve": {},
    "postProcess": true
  }
}