{
  "hash": "c53ac01095ae732b0ac48de8d0cb93e7",
  "result": {
    "markdown": "---\ntitle: \"Stops a Spark Stream\"\nexecute:\n  freeze: true\n---\n\n\n\n\n*R/stream_operations.R*\n\n## stream_stop\n\n## Description\nStops processing data from a Spark stream. \n\n\n## Usage\n```r\nstream_stop(stream) \n```\n\n## Arguments\n|Arguments|Description|\n|---|---|\n| stream | The spark stream object to be stopped. |\n\n\n\n\n\n\n\n\n\n\n",
    "supporting": [],
    "filters": [
      "rmarkdown/pagebreak.lua"
    ],
    "includes": {},
    "engineDependencies": {},
    "preserve": {},
    "postProcess": true
  }
}